{
  "version": 1,
  "name": "Tomo Official Plugins",
  "plugins": [
    {
      "id": "gutenberg",
      "name": "Project Gutenberg",
      "version": "2026-05-23T17:44:29Z",
      "description": "Search and download public-domain books from Project Gutenberg.",
      "homepage": "https://www.gutenberg.org",
      "author": "Tomo",
      "license": "MIT",
      "minAppVersion": "1.7.0",
      "url": "https://raw.githubusercontent.com/pdrbrnd/tomo-plugins/main/plugins/gutenberg.js",
      "sha256": "939087e07ce3a6c78968213353efe95b15f59a37302432eb5f8c752bf8daea27"
    }
  ]
}
